hhi/config.py
hhi/tech.py
hhi/__init__.py
hhi/cli.py
hhi/layers.yaml
hhi/models_deprecated.py
hhi/cells/waveguides.py
hhi/cells/die.py
hhi/cells/fixed.py
hhi/cells/__init__.py
hhi/klayout/layers.lyp
hhi/klayout/tech.lyt
hhi/models/__init__.py
hhi/models/hhi_fixed.py
hhi/models/straights.py
hhi/models/HHI_PDK_6_22_0_bb_performance_numeric/HHI_PDRFtwin.csvy
hhi/models/HHI_PDK_6_22_0_bb_performance_numeric/HHI_ELECTRO_OPTIC_MODULATOR_N20_S21_data.csvy
hhi/models/HHI_PDK_6_22_0_bb_performance_numeric/HHI_PIN_DIODE_data.csvy
hhi/models/HHI_PDK_6_22_0_bb_performance_numeric/HHI_PDDC_dark_current.csvy
hhi/models/HHI_PDK_6_22_0_bb_performance_numeric/HHI_MIR1.csvy
hhi/models/HHI_PDK_6_22_0_bb_performance_numeric/HHI_BJsingle.csvy
hhi/models/HHI_PDK_6_22_0_bb_performance_numeric/HHI_SSCLATE1700.csvy
hhi/models/HHI_PDK_6_22_0_bb_performance_numeric/HHI_STRAIGHT_WG_E600_data.csvy
hhi/models/HHI_PDK_6_22_0_bb_performance_numeric/HHI_GRAT.csvy
hhi/models/HHI_PDK_6_22_0_bb_performance_numeric/HHI_SSCLATE200.csvy
hhi/models/HHI_PDK_6_22_0_bb_performance_numeric/HHI_DirCoupE1700.csvy
hhi/models/HHI_PDK_6_22_0_bb_performance_numeric/HHI_WGTE200E1700.csvy
hhi/models/HHI_PDK_6_22_0_bb_performance_numeric/HHI_BJtwin.csvy
hhi/models/HHI_PDK_6_22_0_bb_performance_numeric/HHI_DFB_1540_EMISSION_SPECTRUM_data.csvy
hhi/models/HHI_PDK_6_22_0_bb_performance_numeric/HHI_EOPMTermination_data.csvy
hhi/models/HHI_PDK_6_22_0_bb_performance_numeric/HHI_DFB_1540_LI_data.csvy
hhi/models/HHI_PDK_6_22_0_bb_performance_numeric/HHI_ELECTRO_ABSORPTION_MODULATOR_L200_data.csvy
hhi/models/HHI_PDK_6_22_0_bb_performance_numeric/HHI_MZMDD.csvy
hhi/models/HHI_PDK_6_22_0_bb_performance_numeric/HHI_ELECTRO_OPTIC_MODULATOR_N12_S21_data.csvy
hhi/models/HHI_PDK_6_22_0_bb_performance_numeric/HHI_PolSplitter.csvy
hhi/models/HHI_PDK_6_22_0_bb_performance_numeric/HHI_STRAIGHT_WG_E1700_data.csvy
hhi/models/HHI_PDK_6_22_0_bb_performance_numeric/HHI_DFB_RIN.csvy
hhi-6.22.1.dist-info/RECORD
hhi-6.22.1.dist-info/WHEEL
hhi-6.22.1.dist-info/entry_points.txt
hhi-6.22.1.dist-info/top_level.txt
hhi-6.22.1.dist-info/METADATA
hhi-6.22.1.dist-info/licenses/LICENSE
