Metadata-Version: 2.4
Name: hhi
Version: 6.22.1
Summary: HHI photonics PDK
Author-email: GDSFactory <contact@gdsfactory.com>
License: The MIT License (MIT)
Keywords: python
Classifier: Programming Language :: Python :: 3.12
Classifier: Operating System :: OS Independent
Requires-Python: ~=3.12.0
License-File: LICENSE
Requires-Dist: gdsfactoryplus
Requires-Dist: gdsfactory~=9.33.0
Provides-Extra: dev
Requires-Dist: gplugins[femwell,sax,tidy3d]~=2.0.1; extra == "dev"
Requires-Dist: build; extra == "dev"
Requires-Dist: cython; extra == "dev"
Requires-Dist: pre-commit; extra == "dev"
Requires-Dist: pytest; extra == "dev"
Requires-Dist: pytest-cov; extra == "dev"
Requires-Dist: pytest_regressions; extra == "dev"
Requires-Dist: ruff; extra == "dev"
Requires-Dist: pytest-github-actions-annotate-failures; extra == "dev"
Requires-Dist: pyppeteer; extra == "dev"
Provides-Extra: docs
Requires-Dist: matplotlib; extra == "docs"
Requires-Dist: jupyter-book==1.0.4; extra == "docs"
Requires-Dist: sphinx-autodoc-typehints; extra == "docs"
Provides-Extra: maintain
Requires-Dist: tbump; extra == "maintain"
Requires-Dist: towncrier; extra == "maintain"
Requires-Dist: ruff; extra == "maintain"
Dynamic: license-file
